xfoil.cpython-311-darwin.so
pyfoil/__init__.py
pyfoil/airfoil.py
pyfoil/py.typed
pyfoil/generators/__init__.py
pyfoil/generators/joukowsy.py
pyfoil/generators/naca.py
pyfoil/generators/treffz.py
pyfoil/generators/vandevooren.py
xfoil-stubs/__init__.pyi
pyfoil-0.1.8.dist-info/METADATA
pyfoil-0.1.8.dist-info/WHEEL
pyfoil-0.1.8.dist-info/top_level.txt
pyfoil-0.1.8.dist-info/RECORD
