Metadata-Version: 2.1
Name: pyfoil
Version: 0.1.8
Summary: python library for airfoil generation, modification and analysis (xfoil included)
Home-page: http://github.com/airgproducts/pyfoil
Author: airgproducts
License: GPL-V3
Requires-Dist: euklid
Requires-Dist: pandas
